w2n_converter/__init__.py
w2n_converter-0.1.0.dist-info/licenses/LICENSE
w2n_converter-0.1.0.dist-info/METADATA
w2n_converter-0.1.0.dist-info/WHEEL
w2n_converter-0.1.0.dist-info/top_level.txt
w2n_converter-0.1.0.dist-info/RECORD
