Metadata-Version: 2.4
Name: w2n_converter
Version: 0.1.0
Summary: Converts an English word to a list of numbers corresponding to the positions of the letters in the English alphabet (a=1, ..., z=26)
Author: Diyorbekw
Author-email: diyorbek0143@gmail.com
Classifier: Programming Language :: Python :: 3
Classifier: License :: OSI Approved :: MIT License
Requires-Python: >=3.7
License-File: LICENSE
Dynamic: author
Dynamic: author-email
Dynamic: classifier
Dynamic: license-file
Dynamic: requires-python
Dynamic: summary
